.DS_Store
Redberry-0.0.7.15.dist-info/DESCRIPTION.rst
Redberry-0.0.7.15.dist-info/METADATA
Redberry-0.0.7.15.dist-info/RECORD
Redberry-0.0.7.15.dist-info/WHEEL
Redberry-0.0.7.15.dist-info/metadata.json
Redberry-0.0.7.15.dist-info/top_level.txt
forms/__init__.py
forms/category.py
forms/post.py
models/__init__.py
models/category.py
models/migrate.py
models/post.py
redberry/__init__.py
redberry/blueprint.py
redberry/forms/__init__.py
redberry/forms/category.py
redberry/forms/post.py
redberry/models/__init__.py
redberry/models/category.py
redberry/models/migrate.py
redberry/models/post.py
redberry/models/version.py
redberry/models/migrations/201612311100_add_content_summary.py
redberry/models/migrations/201612311100_add_publish_state.py
redberry/models/migrations/201612311300_dummy.py
redberry/models/migrations/201805290800_add_hero_image_to_posts.py
redberry/models/migrations/__init__.py
redberry/static/.DS_Store
redberry/static/redberry/.DS_Store
redberry/static/redberry/sitemap.xml
redberry/static/redberry/symbol-defs.svg
redberry/static/redberry/css/redberry.css
redberry/static/redberry/css/trumbowyg.min.css
redberry/static/redberry/js/redberry.js
redberry/static/redberry/js/redberry_admin.js
redberry/static/redberry/js/restful.min.js
redberry/static/redberry/js/trumbowyg.min.js
redberry/static/redberry/js/trumbowyg.preformatted.min.js
redberry/static/redberry/js/trumbowyg.table.min.js
redberry/static/redberry/svg/icons.svg
redberry/templates/.DS_Store
redberry/templates/redberry/.DS_Store
redberry/templates/redberry/_base.html
redberry/templates/redberry/_flashed_messages.html
redberry/templates/redberry/_head.amp.html
redberry/templates/redberry/_head.html
redberry/templates/redberry/_jumbotron.html
redberry/templates/redberry/_macros.html
redberry/templates/redberry/_post.html
redberry/templates/redberry/amp.css.html
redberry/templates/redberry/author.html
redberry/templates/redberry/category.html
redberry/templates/redberry/index.html
redberry/templates/redberry/post.html
redberry/templates/redberry/symbol-defs.svg
redberry/templates/redberry/admin/_categories.html
redberry/templates/redberry/admin/_posts.html
